bettertkinter/BTk.py
bettertkinter/BTkButton.py
bettertkinter/BTkCheckBox.py
bettertkinter/BTkColorPicker.py
bettertkinter/BTkDialog.py
bettertkinter/BTkEntry.py
bettertkinter/BTkFrame.py
bettertkinter/BTkLabel.py
bettertkinter/BTkNavBar.py
bettertkinter/BTkProgressBar.py
bettertkinter/BTkSlider.py
bettertkinter/BTkSwitch.py
bettertkinter/BTkSystemTray.py
bettertkinter/BTkTextEditor.py
bettertkinter/BTkTooltip.py
bettertkinter/__init__.py
bettertkinter-2.0.1.dist-info/licenses/LICENSE
bettertkinter-2.0.1.dist-info/METADATA
bettertkinter-2.0.1.dist-info/WHEEL
bettertkinter-2.0.1.dist-info/dependency_links.txt
bettertkinter-2.0.1.dist-info/entry_points.txt
bettertkinter-2.0.1.dist-info/top_level.txt
bettertkinter-2.0.1.dist-info/RECORD
