Metadata-Version: 2.4
Name: BetterTkinter
Version: 2.0.1
Summary: The ultimate modern UI toolkit for Python - beautiful, customizable widgets with advanced features
Home-page: https://github.com/Velyzo/BetterTkinter
Download-URL: https://github.com/Velyzo/BetterTkinter/archive/refs/tags/v2.0.0.tar.gz
Author: BetterTkinter Team
Author-email: contact@bettertkinter.dev
License: MIT
Project-URL: Bug Tracker, https://github.com/Velyzo/BetterTkinter/issues
Project-URL: Documentation, https://Velyzo.github.io/BetterTkinterDocs/
Project-URL: Source Code, https://github.com/Velyzo/BetterTkinter
Project-URL: Changelog, https://github.com/Velyzo/BetterTkinter/blob/main/CHANGELOG.md
Project-URL: Demo, https://github.com/Velyzo/BetterTkinter/blob/main/bettertkinter/BTkDemo.py
Keywords: tkinter gui ui custom-widgets modern design beautiful python desktop
Classifier: Development Status :: 5 - Production/Stable
Classifier: Programming Language :: Python :: 3
Classifier: Programming Language :: Python :: 3.7
Classifier: Programming Language :: Python :: 3.8
Classifier: Programming Language :: Python :: 3.9
Classifier: Programming Language :: Python :: 3.10
Classifier: Programming Language :: Python :: 3.11
Classifier: Programming Language :: Python :: 3.12
Classifier: License :: OSI Approved :: MIT License
Classifier: Operating System :: OS Independent
Classifier: Intended Audience :: Developers
Classifier: Topic :: Software Development :: Libraries :: Application Frameworks
Classifier: Topic :: Software Development :: User Interfaces
Classifier: Topic :: Software Development :: Widget Sets
Classifier: Environment :: X11 Applications
Classifier: Environment :: Win32 (MS Windows)
Classifier: Environment :: MacOS X
Requires-Python: >=3.7
License-File: LICENSE
Requires-Dist: Pillow>=8.0.0
Provides-Extra: dev
Requires-Dist: pytest>=6.0; extra == "dev"
Requires-Dist: black; extra == "dev"
Requires-Dist: flake8; extra == "dev"
Provides-Extra: full
Requires-Dist: Pillow>=8.0.0; extra == "full"
Requires-Dist: colorsys; extra == "full"
Dynamic: author
Dynamic: author-email
Dynamic: classifier
Dynamic: description
Dynamic: description-content-type
Dynamic: download-url
Dynamic: home-page
Dynamic: keywords
Dynamic: license
Dynamic: license-file
Dynamic: project-url
Dynamic: provides-extra
Dynamic: requires-dist
Dynamic: requires-python
Dynamic: summary
